[
  {
    "id": 1,
    "name": "Mango",
    "tweets": 111,
    "followers": 111500,
    "avatar": "https://uamodna.com/assets/articles/image/5/t/9/5t94dohv/fullsize.jpg"
  },
  {
    "id": 2,
    "name": "Polly",
    "tweets": 222,
    "followers": 22500,
    "avatar": "https://www.5.ua/media/pictures/original/235971.jpg?t=1637675532"
  },
  {
    "id": 3,
    "name": "Alex",
    "tweets": 333,
    "followers": 30500,
    "avatar": "https://encrypted-tbn0.gstatic.com/images?q=tbn:ANd9GcSi6IWeQ3kGsIcC9EoMfX915V1oGPyLTVu1QN9z97MyaCZCwxcaUi8zszFYlH8wkkbSst0&usqp=CAU"
  },
  {
    "id": 4,
    "name": "Ajax",
    "tweets": 444,
    "followers": 4500,
    "avatar": "https://life.pravda.com.ua/images/doc/6/2/623ea24-tvar-1.jpg"
  },
  {
    "id": 5,
    "name": "Riki",
    "tweets": 555,
    "followers": 555000,
    "avatar": "https://lifeimg.pravda.com/images/doc/f/b/fb2a4b7-depositphotos-evakid-633.jpg"
  },
  {
    "id": 6,
    "name": "Pikachu",
    "tweets": 667,
    "followers": 64500,
    "avatar": "https://www.poglyad.tv/wp-content/uploads/2020/02/05_zakon.jpg"
  },
  {
    "id": 7,
    "name": "Niki",
    "tweets": 777,
    "followers": 75700,
    "avatar": "https://www.ugorod.kr.ua/cache/images/news/f2/64568_600x450.jpg"
  }
]
